glorpen/wallpaper_picker/__init__.py
glorpen/wallpaper_picker/__main__.py
glorpen/wallpaper_picker/cli.py
glorpen/wallpaper_picker/image.py
glorpen/wallpaper_picker/models.py
glorpen/wallpaper_picker/screen.py
glorpen/wallpaper_picker/wallpaper.py
glorpen/wallpaper_picker/backend/__init__.py
glorpen/wallpaper_picker/backend/wayland.py
glorpen/wallpaper_picker/backend/xorg.py
glorpen_wallpaper_picker-1.1.3.dist-info/LICENSE
glorpen_wallpaper_picker-1.1.3.dist-info/METADATA
glorpen_wallpaper_picker-1.1.3.dist-info/WHEEL
glorpen_wallpaper_picker-1.1.3.dist-info/entry_points.txt
glorpen_wallpaper_picker-1.1.3.dist-info/top_level.txt
glorpen_wallpaper_picker-1.1.3.dist-info/RECORD
