Metadata-Version: 2.1
Name: glorpen-wallpaper_picker
Version: 1.1.3
Summary: Randomize your wallpaper in a smarter way.
Home-page: https://github.com/glorpen/wallpaper-picker
Author: Arkadiusz Dzięgiel
Author-email: arkadiusz.dziegiel@glorpen.pl
Project-URL: Bug Tracker, https://github.com/glorpen/wallpaper-picker/issues
Classifier: Programming Language :: Python :: 3
Classifier: Environment :: X11 Applications
Classifier: Intended Audience :: End Users/Desktop
Classifier: License :: OSI Approved :: GNU General Public License v3 or later (GPLv3+)
Classifier: Operating System :: POSIX :: Linux
Classifier: Topic :: Desktop Environment
Classifier: Topic :: Utilities
Requires-Python: >=3.11
License-File: LICENSE
Requires-Dist: pillow>=7
Requires-Dist: pyxattr>=0.7
Provides-Extra: xorg
Requires-Dist: xcffib>=0.9; extra == "xorg"
Provides-Extra: wayland
Requires-Dist: python-daemon>=3.0.0; extra == "wayland"
